pbi_vizdata/__init__.py
pbi_vizdata/pbi_visual_extracts.py
pbi_vizdata-0.1.dist-info/METADATA
pbi_vizdata-0.1.dist-info/WHEEL
pbi_vizdata-0.1.dist-info/top_level.txt
pbi_vizdata-0.1.dist-info/RECORD
